ai_hexagon/__init__.py
ai_hexagon/cli.py
ai_hexagon/model.py
ai_hexagon/modules/grouped_query_attention.py
ai_hexagon/modules/mlp.py
ai_hexagon/modules/sin_embedding.py
ai_hexagon/test.py
ai_hexagon/test_suite.py
ai_hexagon/tests/__init__.py
ai_hexagon/tests/hash_map.py
ai_hexagon/tests/state_tracking.py
ai_hexagon-0.1.0.dist-info/LICENSE
ai_hexagon-0.1.0.dist-info/METADATA
ai_hexagon-0.1.0.dist-info/WHEEL
ai_hexagon-0.1.0.dist-info/entry_points.txt
ai_hexagon-0.1.0.dist-info/RECORD
