Metadata-Version: 2.1
Name: ai-hexagon
Version: 0.1.0
Summary: An objective way to evaluate neural network architectures
Author: Jiri Klimes
Author-email: jiriklimes920@gmail.com
Requires-Python: >=3.12,<4.0
Classifier: Programming Language :: Python :: 3
Classifier: Programming Language :: Python :: 3.12
Classifier: Programming Language :: Python :: 3.13
Requires-Dist: click (>=8.1.7,<9.0.0)
Requires-Dist: einops (>=0.8.0,<0.9.0)
Requires-Dist: flax (>=0.9.0,<0.10.0)
Requires-Dist: inflection (>=0.5.1,<0.6.0)
Requires-Dist: jax (>=0.4.34,<0.5.0)
Requires-Dist: optax (>=0.2.3,<0.3.0)
Requires-Dist: pydantic (>=2.9.2,<3.0.0)
Requires-Dist: tabulate (>=0.9.0,<0.10.0)
Requires-Dist: tqdm (>=4.67.0,<5.0.0)
